bwm/__init__.py
bwm/__main__.py
bwm/_version.py
bwm/bwcli.py
bwm/bwedit.py
bwm/bwm.py
bwm/bwtype.py
bwm/bwview.py
bwm/menu.py
bwm/tokens_pynput.py
bwm/tokens_wtype.py
bwm/tokens_xdotool.py
bwm/tokens_ydotool.py
bwm/totp.py
bitwarden_menu-0.4.5.data/data/share/doc/bitwarden-menu/LICENSE
bitwarden_menu-0.4.5.data/data/share/doc/bitwarden-menu/README.md
bitwarden_menu-0.4.5.data/data/share/doc/bitwarden-menu/config.ini.example
bitwarden_menu-0.4.5.data/data/share/doc/bitwarden-menu/docs/configure.md
bitwarden_menu-0.4.5.data/data/share/doc/bitwarden-menu/docs/install.md
bitwarden_menu-0.4.5.data/data/share/doc/bitwarden-menu/docs/short.gif
bitwarden_menu-0.4.5.data/data/share/doc/bitwarden-menu/docs/usage.md
bitwarden_menu-0.4.5.data/data/share/man/man1/bwm.1
bitwarden_menu-0.4.5.dist-info/METADATA
bitwarden_menu-0.4.5.dist-info/WHEEL
bitwarden_menu-0.4.5.dist-info/entry_points.txt
bitwarden_menu-0.4.5.dist-info/licenses/LICENSE
bitwarden_menu-0.4.5.dist-info/RECORD
