Metadata-Version: 2.3
Name: bitwarden-menu
Version: 0.4.5
Summary: Dmenu/Rofi frontend for Bitwarden CLI tool
Project-URL: Homepage, https://github.com/firecat53/bitwarden-menu
Author-email: Scott Hansen <tech@firecat53.net>
License: MIT
Keywords: bitwarden,bitwarden-menu,bwm,dmenu,rofi,wofi
Classifier: Development Status :: 4 - Beta
Classifier: Environment :: Console
Classifier: Environment :: X11 Applications
Classifier: Intended Audience :: End Users/Desktop
Classifier: License :: OSI Approved :: MIT License
Classifier: Programming Language :: Python
Classifier: Programming Language :: Python :: 3.7
Classifier: Programming Language :: Python :: 3.8
Classifier: Programming Language :: Python :: 3.9
Classifier: Programming Language :: Python :: 3.10
Classifier: Programming Language :: Python :: 3.11
Classifier: Programming Language :: Python :: 3.12
Classifier: Programming Language :: Python :: 3.13
Classifier: Topic :: Utilities
Requires-Dist: pynput
Requires-Dist: xdg-base-dirs
